b3q/__init__.py
b3q/b3q.py
b3q-0.4.0.dist-info/LICENSE
b3q-0.4.0.dist-info/METADATA
b3q-0.4.0.dist-info/WHEEL
b3q-0.4.0.dist-info/top_level.txt
b3q-0.4.0.dist-info/RECORD
