Metadata-Version: 2.1
Name: b3q
Version: 0.4.0
Summary: Boto3 utility library that supports parameter-driven and predicate-driven retrieval of collections of AWS resources.
Author: Andrei Lapets
Author-email: a@lapets.io
License: MIT
Project-URL: Repository, https://github.com/nthparty/b3q
Project-URL: Documentation, https://b3q.readthedocs.io
Requires-Python: >=3.7
License-File: LICENSE
Provides-Extra: coveralls
Requires-Dist: coveralls (~=3.3.1) ; extra == 'coveralls'
Provides-Extra: docs
Requires-Dist: toml (~=0.10.2) ; extra == 'docs'
Requires-Dist: sphinx (~=4.2.0) ; extra == 'docs'
Requires-Dist: sphinx-rtd-theme (~=1.0.0) ; extra == 'docs'
Requires-Dist: sphinx-autodoc-typehints (~=1.12.0) ; extra == 'docs'
Provides-Extra: lint
Requires-Dist: pylint (~=2.14.0) ; extra == 'lint'
Provides-Extra: publish
Requires-Dist: build (~=0.8) ; extra == 'publish'
Requires-Dist: twine (~=4.0) ; extra == 'publish'
Provides-Extra: test
Requires-Dist: pytest (~=7.0) ; extra == 'test'
Requires-Dist: pytest-cov (~=3.0) ; extra == 'test'
